{
  "id": "กฎกระทรวงการอนุญาตมีไว้ในครอบครองยาเสพติดให้โทษในป-be2568",
  "type": "statute",
  "title_th": "กฎกระทรวงการอนุญาตมีไว้ในครอบครองยาเสพติดให้โทษในประเภท 2 และวัตถุออกฤทธิ์ในประเภท 2 ประเภท 3 หรือประเภท 4 พ.ศ. 2568",
  "title_en": "",
  "short_name": "กฎกระทรวงการอนุญาตมีไว้ในครอบครองยาเสพติดให้โทษในป 2025",
  "status": "in_force",
  "be_year": 2568,
  "ce_year": 2025,
  "issued_date": "2025-01-01",
  "url": "https://searchlaw.ocs.go.th/council-of-state/#/public/doc/ZTVMdk5iTHBnRWQyemE1R2dYVjU0UT09",
  "provisions": [
    {
      "provision_ref": "sch-undefined",
      "section": "undefined",
      "title": "บทเฉพาะกาล",
      "content": "บทเฉพาะกาล",
      "language": "th"
    },
    {
      "provision_ref": "sch-undefined",
      "section": "undefined",
      "title": "หมายเหตุ",
      "content": "หมายเหตุ :- เหตุผลในการประกาศใช้กฎกระทรวงฉบับนี้ คือ โดยที่มาตรา ๓๕ วรรคสาม และมาตรา ๓๗ วรรคหนึ่ง แห่งประมวลกฎหมายยาเสพติด บัญญัติให้การอนุญาตมีไว้ในครอบครองยาเสพติดให้โทษในประเภท ๒ และวัตถุออกฤทธิ์ในประเภท ๒ ประเภท ๓ หรือประเภท ๔ และการควบคุมกำกับดูแล ให้เป็นไปตามหลักเกณฑ์ วิธีการ และเงื่อนไขที่กำหนดในกฎกระทรวง และมาตรา ๑๘ วรรคหนึ่ง บัญญัติให้กำหนดอัตราค่าธรรมเนียมไม่เกินอัตราตามบัญชีท้ายประมวลกฎหมายนี้หรือยกเว้นค่าธรรมเนียมในกฎกระทรวง  จึงจำเป็นต้องออกกฎกระทรวงนี้",
      "language": "th"
    }
  ]
}