{
  "id": "ประกาศกระทรวงแรงงาน-เรื่อง-กำหนดเจ้าหน้าที่ของรัฐผ-be2566",
  "type": "statute",
  "title_th": "ประกาศกระทรวงแรงงาน เรื่อง กำหนดเจ้าหน้าที่ของรัฐผู้มีอำนาจปรับเป็นพินัยตามพระราชบัญญัติคุ้มครองแรงงาน พ.ศ. 2541",
  "title_en": "",
  "short_name": "ประกาศกระทรวงแรงงาน-เรื่อง-กำหนดเจ้าหน้าที่ของรัฐผ 2023",
  "status": "in_force",
  "be_year": 2566,
  "ce_year": 2023,
  "issued_date": "2023-01-01",
  "url": "https://searchlaw.ocs.go.th/council-of-state/#/public/doc/WVBzclRmd0VpWnl5U0pZRWFGM3M1UT09",
  "provisions": []
}